{
  "Shipping": {
    "Title": "Versanddetails",
    "Labels": {
      "UseMultiple": "An mehrere Adressen versenden",
      "ShippingAddress": "Versandadresse",
      "ShippingMethod": "Versandmethode",
      "SelectShippingMethod": "Gewünschte Versandmethode wählen",
      "AddNewAddress": "Neue Adresse hinzufügen",
      "EditAddress": "Adresse bearbeiten"
    },
    "Actions": {
      "SelectAddress": "Diese Adresse verwenden",
      "CreateNew": "Neue Adresse erstellen",
      "Next": "Weiter zur Zahlung"
    },
    "Msgs": {
      "UseSavedAddress": "Oder wählen Sie eine gespeicherte Adresse aus:",
      "SelectShippingAddress": "Bitte wählen Sie zunächst eine Versandadresse aus"
    }
  }
}
