{
  "Shipping": {
    "Title": "Shipping Details",
    "Labels": {
      "UseMultiple": "Ship to multiple addresses",
      "ShippingAddress": "Адрес доставки",
      "ShippingMethod": "Способ доставки",
      "SelectShippingMethod": "Choose your delivery method",
      "AddNewAddress": "Add new address",
      "EditAddress": "Edit Address"
    },
    "Actions": {
      "SelectAddress": "Use this address",
      "CreateNew": "Create new address",
      "Next": "Continue to Payment"
    },
    "Msgs": {
      "UseSavedAddress": "Or select a saved address to use:",
      "SelectShippingAddress": "Please first select a shipping address"
    }
  }
}
