{
  "BuyerOrganizationRegistration": {
    "OrganizationRegistration": "注册贵组织",
    "BuyerAdminRegistration": "注册管理员",
    "Title": "组织注册",
    "AddressDetails": "地址详细信息",
    "AddressLineAdd": "添加地址行 2",
    "Back": "返回",
    "NextRegister": "下一步，注册管理员",
    "CompleteRegistration": "完成注册",
    "HereAnAccount": "已有帐户？",
    "SignIn": "登录",
    "OrganizationName": "组织名称",
    "AccountPreferences": "帐户首选项",
    "Email": "电子邮件",
    "Address1": "地址行 1",
    "Address2": "地址行 2（可选）",
    "City": "城市",
    "Country": "国家/地区",
    "State": "州/省",
    "ZipCode": "邮政编码/邮编",
    "FirstName": "名字",
    "LastName": "姓氏",
    "LogonId": "登录标识",
    "Phone": "电话（可选）",
    "Password": "密码",
    "Password2": "验证密码",
    "Language": "首选语言",
    "Currency": "首选货币",
    "UseOrganizationAddress": "使用与组织相同的地址",
    "Submit": "提交",
    "Clear": "清除",
    "Success": "已收到您的注册请求。您的帐户正在等待审批。在帐户获批准前，您无法登录。",
    "OK": "确定",
    "Msgs": {
      "InvalidFormat": "无效格式"
    }
  }
}
