{
  "ForgotPassword": {
    "Title": "Esqueceu-se da palavra-passe?",
    "EmailLabel": "Endereço de e-mail",
    "SubmitButton": "Submeter",
    "LogonIDLabel": "ID de início de sessão",
    "ContentText": "Introduza o seu endereço de e-mail. Irá receber um código de verificação para repor a palavra-passe.",
    "ContentTextLogonID": "Introduza o seu ID de início de sessão. Irá receber um código de verificação para repor a palavra-passe através do e-mail da sua conta.",
    "ValidationCodeButton": "Introduzir Código de verificação",
    "SendVerificationCodeButton": "Enviar-me um código de verificação",
    "CodeRecieved": "Já recebeu um código de verificação?",
    "AccountInfoRemember": "Lembrar as informações da sua conta? ",
    "SignIn": "Iniciar sessão agora",
    "Msgs": {
      "InvalidFormat": "Formato inválido"
    }
  }
}
