{
  "Payment": {
    "Title": "Szczegóły płatności",
    "Msgs": {
      "InvalidFormat": "Nieprawidłowy format"
    },
    "Labels": {
      "UseMultiple": "Użyj wielu form płatności",
      "PaymentMethod": "Forma płatności {{number}}",
      "AddNewAddress": "Dodaj nowy adres",
      "BillingAddress": "Adres do faktury"
    },
    "Actions": {
      "Back": "Wróć do szczegółów dostawy",
      "Next": "Przegląd zamówienia",
      "Finish": "Zakończ",
      "SaveAndAdd": "Zapisz i dodaj inną formę płatności",
      "AddAnotherPayMethod": "Dodaj inną formę płatności"
    }
  }
}
