{
  "OrderLinks": {
    "Title": "Order Management",

    "OrderHistoryText": "Order History",
    "OrderHistoryDescription": "View placed orders and orders pending approval, and individual order details.",
    "SavedOrdersText": "Saved Orders",
    "SavedOrdersDescription": "View and manage saved orders",

    "RecurringOrdersText": "Recurring Orders",
    "RecurringOrdersDescription": "View and manage list of recurring orders",
    "ApproveOrdersText": "Approve Orders",
    "ApproveOrdersDescription": "Approve or reject orders",

    "RequisitionListsText": "Requisition Lists",
    "RequisitionListsDescription": "View, manage and create requisition lists"
  }
}
